cdxbasics/__init__.py
cdxbasics/cached.py
cdxbasics/config.py
cdxbasics/crman.py
cdxbasics/deferred.py
cdxbasics/dynaplot.py
cdxbasics/filelock.py
cdxbasics/jcpool.py
cdxbasics/kwargs.py
cdxbasics/logger.py
cdxbasics/np.py
cdxbasics/npio.py
cdxbasics/prettydict.py
cdxbasics/prettyobject.py
cdxbasics/sharedarray.py
cdxbasics/subdir.py
cdxbasics/util.py
cdxbasics/vcache.py
cdxbasics/verbose.py
cdxbasics/version.py
cdxbasics-0.2.141.dist-info/LICENSE
cdxbasics-0.2.141.dist-info/METADATA
cdxbasics-0.2.141.dist-info/WHEEL
cdxbasics-0.2.141.dist-info/top_level.txt
cdxbasics-0.2.141.dist-info/RECORD
