Metadata-Version: 2.1
Name: cdxbasics
Version: 0.2.141
Summary: Basic Python tools
Home-page: https://github.com/hansbuehler/cdxbasics
Author: Hans Buehler
Author-email: github@buehler.london
Classifier: Programming Language :: Python :: 3
Classifier: License :: OSI Approved :: MIT License
Classifier: Operating System :: OS Independent
Requires-Python: >=3.8
License-File: LICENSE
Requires-Dist: numpy
Requires-Dist: pandas
Requires-Dist: matplotlib
Requires-Dist: sortedcontainers
Requires-Dist: psutil
Requires-Dist: jsonpickle
Requires-Dist: setuptools
Requires-Dist: numba
